denstream/__init__.py
denstream/den_stream.py
denstream/micro_cluster.py
denstream/preprocessing.py
denstream/typing.py
denstream/utils.py
denstream-0.1.4.dist-info/METADATA
denstream-0.1.4.dist-info/WHEEL
denstream-0.1.4.dist-info/licenses/LICENSE
denstream-0.1.4.dist-info/RECORD
