Metadata-Version: 2.4
Name: denstream
Version: 0.1.4
Summary: Implementation of the DenStream algorithm
Author: MrParosk
License-File: LICENSE
Requires-Python: <3.14,>=3.9
Requires-Dist: numba>=0.56
Requires-Dist: numpy>=2.0
Requires-Dist: scikit-learn>=1.0
Requires-Dist: typing-extensions>=4.14.0
